pycrdt/store/__init__.py
pycrdt/store/base.py
pycrdt/store/file.py
pycrdt/store/py.typed
pycrdt/store/sqlite.py
pycrdt/store/utils.py
pycrdt_store-0.1.3.dist-info/METADATA
pycrdt_store-0.1.3.dist-info/WHEEL
pycrdt_store-0.1.3.dist-info/licenses/LICENSE
pycrdt_store-0.1.3.dist-info/RECORD
