Metadata-Version: 2.4
Name: pycrdt-store
Version: 0.1.3
Summary: Persistent storage for pycrdt
Project-URL: Homepage, https://github.com/y-crdt/pycrdt-store
Project-URL: Source, https://github.com/y-crdt/pycrdt-store
Project-URL: Issues, https://github.com/y-crdt/pycrdt-store/issues
Project-URL: Pypi, https://pypi.org/project/pycrdt-store
Author-email: David Brochart <david.brochart@gmail.com>
License: MIT License
License-File: LICENSE
Keywords: pycrdt,yjs
Classifier: Development Status :: 4 - Beta
Classifier: Intended Audience :: Developers
Classifier: License :: OSI Approved :: MIT License
Classifier: Programming Language :: Python
Classifier: Programming Language :: Python :: 3.9
Classifier: Programming Language :: Python :: 3.10
Classifier: Programming Language :: Python :: 3.11
Classifier: Programming Language :: Python :: 3.12
Classifier: Programming Language :: Python :: 3.13
Requires-Python: >=3.9
Requires-Dist: anyio<5,>=3.6.2
Requires-Dist: pycrdt<0.13.0,>=0.12.13
Requires-Dist: sqlite-anyio<0.3.0,>=0.2.3
Provides-Extra: docs
Requires-Dist: mkdocs; extra == 'docs'
Requires-Dist: mkdocs-material; extra == 'docs'
Requires-Dist: mkdocstrings-python; extra == 'docs'
Provides-Extra: test
Requires-Dist: mypy; extra == 'test'
Requires-Dist: pre-commit; extra == 'test'
Requires-Dist: pytest; extra == 'test'
Requires-Dist: pytest-rerunfailures; extra == 'test'
Requires-Dist: trio>=0.25.0; extra == 'test'
